brain_diffusion/__init__.py
brain_diffusion/histogram_utils.py
brain_diffusion/hyak_msd_template.py
brain_diffusion/msd.py
brain_diffusion/version.py
brain_diffusion-0.1.dev0.dist-info/DESCRIPTION.rst
brain_diffusion-0.1.dev0.dist-info/METADATA
brain_diffusion-0.1.dev0.dist-info/RECORD
brain_diffusion-0.1.dev0.dist-info/WHEEL
brain_diffusion-0.1.dev0.dist-info/metadata.json
brain_diffusion-0.1.dev0.dist-info/top_level.txt
