Metadata-Version: 2.0
Name: brain-diffusion
Version: 0.1.dev0
Summary: brain_diffusion: a tool for calculating and analyzing MSDs from trajectory datasets
Home-page: https://github.com/ccurtis7/brain_diffusion
Author: Chad Curtis
Author-email: ccurtis7@uw.edu
License: BSD
Platform: OS Independent
Classifier: Development Status :: 3 - Alpha
Classifier: Environment :: Console
Classifier: License :: OSI Approved :: BSD License
Classifier: Operating System :: OS Independent
Classifier: Programming Language :: Python
Requires: numpy
Requires: scipy
Requires: matplotlib
Requires-Dist: matplotlib
Requires-Dist: numpy
Requires-Dist: scipy
